TOBARA/__init__.py
TOBARA/func_detectRectangle.py
TOBARA/func_getBin.py
TOBARA/func_getKmap.py
TOBARA/func_getMinTable.py
TOBARA/func_getTable.py
TOBARA/func_reduceFun.py
TOBARA/func_reduceKmap.py
TOBARA/main.py
TOBARA-1.0.3.dist-info/LICENSE
TOBARA-1.0.3.dist-info/METADATA
TOBARA-1.0.3.dist-info/WHEEL
TOBARA-1.0.3.dist-info/top_level.txt
TOBARA-1.0.3.dist-info/RECORD
