Metadata-Version: 2.1
Name: TOBARA
Version: 1.0.3
Summary: TOBARA (The Only Boolean Algebra Reduction App) is a toolkit of Boolean function analysis whose main task is to reduce Boolean functions as much as possible. Our objetive is to determine information about the function like variables, terms and then reduce the function.
Home-page: https://github.com/MiguelRAvila/projectTOBARA
Author: Miguel R. Ávila
Author-email: miguelravila@outlook.com
License: UNKNOWN
Platform: UNKNOWN
Classifier: Programming Language :: Python :: 3
Classifier: License :: OSI Approved :: MIT License
Classifier: Operating System :: OS Independent
Requires-Python: >=3.6
